{
    "-NelJG5rikofEohlb4X2": {
      "Device": "iOS,Safari",
      "Email": "ogm.wd.intern4@gmail.com",
      "Fullname": "Art Lisboa",
      "Number": "1231231231",
      "Organization": "asdasd",
      "Password": "YXNkYXNk",
      "Status": "Pending",
      "date": [
        "9/20/2023",
        "2:39:54 PM"
      ],
      "id": "-NelJG5rikofEohlb4X2"
    },
    "-Nepl7kQvu3XD6G-3mIG": {
      "Device": "Windows,Chrome",
      "Email": "ajderoque@gmail.com",
      "Fullname": "Aj kinikilig",
      "Number": "0915446920",
      "Organization": "OGM",
      "Password": "aGFoYWhhaGE=",
      "Status": "Pending",
      "date": [
        "9/21/2023",
        "11:24:31 AM"
      ],
      "id": "-Nepl7kQvu3XD6G-3mIG"
    },
    "hUaF4KDUllTCmDbr8eeWzC5DIEv2": {
      "Device": "iOS,Safari",
      "Email": "hellofriend@gmail.com",
      "Fullname": "Hello Friend",
      "Number": "0000000000",
      "Organization": "asdasd",
      "Password": "YXNkYXNk",
      "Status": "Granted",
      "date": [
        "9/19/2023",
        "2:39:54 PM"
      ],
      "id": "hUaF4KDUllTCmDbr8eeWzC5DIEv2"
    },
    "nl5w0JzrRUXkBj7GF8GAZIURSil1": {
      "Device": "iOS,Safari",
      "Email": "wellnesspro_admin@gmail.com",
      "Fullname": "Wellness Pro",
      "Number": "0000000000",
      "Organization": "asdasd",
      "Password": "YXNkYXNk",
      "Status": "Granted",
      "date": [
        "9/6/2023",
        "2:39:54 PM"
      ],
      "id": "nl5w0JzrRUXkBj7GF8GAZIURSil1"
    }
  }